<?xml version="1.0"?>
<config xmlns="http://tail-f.com/ns/config/1.0">
  <interface xmlns="urn:ios">
    <Loopback>
      <name>0</name>
    </Loopback>
    <GigabitEthernet>
      <name>0/1</name>
    </GigabitEthernet>
    <GigabitEthernet>
      <name>0/2</name>
    </GigabitEthernet>
    <GigabitEthernet>
      <name>0/3</name>
    </GigabitEthernet>
    <GigabitEthernet>
      <name>0/4</name>
    </GigabitEthernet>
    <GigabitEthernet>
      <name>0/5</name>
    </GigabitEthernet>
    <GigabitEthernet>
      <name>0/6</name>
    </GigabitEthernet>
    <GigabitEthernet>
      <name>0/7</name>
    </GigabitEthernet>
    <GigabitEthernet>
      <name>0/8</name>
    </GigabitEthernet>
    <GigabitEthernet>
      <name>0/9</name>
    </GigabitEthernet>
    <GigabitEthernet>
      <name>0/10</name>
    </GigabitEthernet>
    <GigabitEthernet>
      <name>0/11</name>
    </GigabitEthernet>
    <GigabitEthernet>
      <name>0/12</name>
    </GigabitEthernet>
    <GigabitEthernet>
      <name>0/13</name>
    </GigabitEthernet>
    <GigabitEthernet>
      <name>0/14</name>
    </GigabitEthernet>
    <GigabitEthernet>
      <name>0/15</name>
    </GigabitEthernet>
    <GigabitEthernet>
      <name>0/16</name>
    </GigabitEthernet>
    <GigabitEthernet>
      <name>0/17</name>
    </GigabitEthernet>
    <GigabitEthernet>
      <name>0/18</name>
    </GigabitEthernet>
    <GigabitEthernet>
      <name>0/19</name>
    </GigabitEthernet>
    <GigabitEthernet>
      <name>0/20</name>
    </GigabitEthernet>
    <GigabitEthernet>
      <name>0/21</name>
    </GigabitEthernet>
    <GigabitEthernet>
      <name>0/22</name>
    </GigabitEthernet>
    <GigabitEthernet>
      <name>0/23</name>
    </GigabitEthernet>
    <GigabitEthernet>
      <name>0/24</name>
    </GigabitEthernet>
  </interface>
  </config>
